setup.py
xclarity_client/__init__.py
xclarity_client/client.py
xclarity_client/constants.py
xclarity_client/exceptions.py
xclarity_client/xclarity_client.py
xclarity_client.egg-info/PKG-INFO
xclarity_client.egg-info/SOURCES.txt
xclarity_client.egg-info/dependency_links.txt
xclarity_client.egg-info/entry_points.txt
xclarity_client.egg-info/not-zip-safe
xclarity_client.egg-info/top_level.txt
xclarity_client/v1_2_2/__init__.py
xclarity_client/v1_2_2/boot_order.py
xclarity_client/v1_2_2/client.py